LICENSE
MANIFEST.in
README.rst
setup.cfg
setup.py
callgraphdecorator/__init__.py
callgraphdecorator/decorator.py
callgraphdecorator.egg-info/PKG-INFO
callgraphdecorator.egg-info/SOURCES.txt
callgraphdecorator.egg-info/dependency_links.txt
callgraphdecorator.egg-info/requires.txt
callgraphdecorator.egg-info/top_level.txt