Metadata-Version: 1.1
Name: callgraphdecorator
Version: 1.0.1
Summary: Decorator for easy use PyCallGraph
Home-page: https://github.com/p-eli/pycallgraphdecorator
Author: Jakub Pelikan
Author-email: jakub.pelikan@gmail.com
License:                     GNU GENERAL PUBLIC LICENSE
